im2deep/__init__.py
im2deep/__main__.py
im2deep/_exceptions.py
im2deep/calibrate.py
im2deep/im2deep.py
im2deep/predict_multi.py
im2deep/utils.py
im2deep/models/TIMS/full_hc_peprec_CCS_v4_1fd8363d9af9dcad3be7553c39396960.keras
im2deep/models/TIMS/full_hc_peprec_CCS_v4_8c22d89667368f2f02ad996469ba157e.keras
im2deep/models/TIMS/full_hc_peprec_CCS_v4_cb975cfdd4105f97efa0b3afffe075cc.keras
im2deep/models/TIMS_multi/multi_output.ckpt
im2deep/models/TIMS_multi/multi_output_backbone.ckpt
im2deep/models/TIMS_multi/multi_output_pre_revision.ckpt
im2deep/reference_data/multi_reference_ccs.gz
im2deep/reference_data/reference_ccs.zip
im2deep-1.2.0.dist-info/licenses/LICENSE
im2deep-1.2.0.dist-info/METADATA
im2deep-1.2.0.dist-info/WHEEL
im2deep-1.2.0.dist-info/entry_points.txt
im2deep-1.2.0.dist-info/top_level.txt
im2deep-1.2.0.dist-info/RECORD
