Metadata-Version: 2.4
Name: im2deep
Version: 1.2.0
Summary: Framework for prediction of collisional cross-section of peptides.
Author-email: Robbe Devreese <robbe.devreese@ugent.be>, Robbin Bouwmeester <robbin.bouwmeester@ugent.be>, Ralf Gabriels <ralf@gabriels.dev>
License:                                  Apache License
Project-URL: GitHub, https://github.com/CompOmics/IM2Deep
Project-URL: CompOmics, https://www.compomics.com
Keywords: proteomics,peptide,timsTOF,CCS
Classifier: Intended Audience :: Science/Research
Classifier: License :: OSI Approved :: Apache Software License
Classifier: Operating System :: OS Independent
Classifier: Programming Language :: Python :: 3 :: Only
Classifier: Topic :: Scientific/Engineering :: Bio-Informatics
Requires-Python: >=3.10
License-File: LICENSE
Requires-Dist: click
Requires-Dist: deeplc<4
Requires-Dist: psm_utils
Requires-Dist: pandas
Requires-Dist: numpy
Requires-Dist: rich
Provides-Extra: dev
Requires-Dist: black>=23.0; extra == "dev"
Requires-Dist: isort>=5.12; extra == "dev"
Requires-Dist: pytest>=7.0; extra == "dev"
Requires-Dist: pytest-cov>=4.0; extra == "dev"
Requires-Dist: pytest-mock>=3.10; extra == "dev"
Requires-Dist: mypy>=1.0; extra == "dev"
Requires-Dist: pre-commit>=3.0; extra == "dev"
Provides-Extra: docs
Requires-Dist: sphinx>=6.0; extra == "docs"
Requires-Dist: numpydoc>=1.5; extra == "docs"
Requires-Dist: recommonmark>=0.7; extra == "docs"
Requires-Dist: sphinx-mdinclude>=0.5; extra == "docs"
Requires-Dist: toml>=0.10; extra == "docs"
Requires-Dist: semver>=2.13; extra == "docs"
Requires-Dist: sphinx_rtd_theme>=1.2; extra == "docs"
Requires-Dist: sphinx-autobuild>=2021.3; extra == "docs"
Provides-Extra: er
Requires-Dist: im2deeptrainer; extra == "er"
Requires-Dist: torch==2.3.0; extra == "er"
Dynamic: license-file
